Metadata-Version: 2.1
Name: ta-assignment-automation
Version: 0.1
Summary: Assign TAs to Classes using a global optimization algorithm
Home-page: https://github.com/AshwinkumarPillai/TA_assignment_automation
Author: Ashwin Pillai
Author-email: ashwinkumarpillai1729@gmail.com
License: MIT
Requires-Dist: numpy
Requires-Dist: pandas
